README.md
setup.py
staller/__init__.py
staller/jpache.py
staller/shib_it.py
staller/solr_it.py
staller/staller.py
staller/test.py
staller/wtf.py
staller.egg-info/PKG-INFO
staller.egg-info/SOURCES.txt
staller.egg-info/dependency_links.txt
staller.egg-info/entry_points.txt
staller.egg-info/requires.txt
staller.egg-info/top_level.txt