Metadata-Version: 1.0
Name: staller
Version: 0.4.5
Summary: Small application to find the latest version of a softwarepackage, download it, check the PGP signature, check the checksums, and install it.
Home-page: https://github.com/ucldc/staller
Author: California Digital Library
Author-email: UNKNOWN
License: BSD
Platform: UNKNOWN
